build/lib/openff/nagl_models/__init__.py
build/lib/openff/nagl_models/_dynamic_fetch.py
build/lib/openff/nagl_models/_version.py
build/lib/openff/nagl_models/openff_nagl_models.py
build/lib/openff/nagl_models/tests/test_dynamic_fetch.py
build/lib/openff/nagl_models/tests/test_model_performance.py
build/lib/openff/nagl_models/tests/test_openff_nagl_models.py
docs/conf.py
openff/nagl_models/__init__.py
openff/nagl_models/_dynamic_fetch.py
openff/nagl_models/_version.py
openff/nagl_models/openff_nagl_models.py
openff/nagl_models/__pycache__/__init__.cpython-310.pyc
openff/nagl_models/__pycache__/__init__.cpython-311.pyc
openff/nagl_models/__pycache__/_dynamic_fetch.cpython-310.pyc
openff/nagl_models/__pycache__/_version.cpython-310.pyc
openff/nagl_models/__pycache__/_version.cpython-311.pyc
openff/nagl_models/__pycache__/openff_nagl_models.cpython-310.pyc
openff/nagl_models/__pycache__/openff_nagl_models.cpython-311.pyc
openff/nagl_models/models/README.md
openff/nagl_models/models/openff-gnn-am1bcc-0.0.1-alpha.1.pt
openff/nagl_models/models/openff-gnn-am1bcc-0.1.0-rc.1.pt
openff/nagl_models/models/am1bcc/openff-gnn-am1bcc-0.0.1-alpha.1.pt
openff/nagl_models/models/am1bcc/openff-gnn-am1bcc-0.1.0-rc.1.pt
openff/nagl_models/models/am1bcc/openff-gnn-am1bcc-0.1.0-rc.2.pt
openff/nagl_models/models/am1bcc/openff-gnn-am1bcc-0.1.0-rc.3.pt
openff/nagl_models/models/am1bcc/openff-gnn-am1bcc-1.0.0.pt
openff/nagl_models/models/am1bcc/.ipynb_checkpoints/Untitled-checkpoint.ipynb
openff/nagl_models/tests/test_dynamic_fetch.py
openff/nagl_models/tests/test_model_performance.py
openff/nagl_models/tests/test_openff_nagl_models.py
openff/nagl_models/tests/__pycache__/test_model_performance.cpython-310-pytest-7.4.3.pyc
openff/nagl_models/tests/__pycache__/test_model_performance.cpython-310-pytest-8.0.0.pyc
openff/nagl_models/tests/__pycache__/test_model_performance.cpython-311-pytest-7.4.0.pyc
openff/nagl_models/tests/__pycache__/test_openff_nagl_models.cpython-310-pytest-7.4.3.pyc
openff_nagl_models-2025.9.0.dist-info/licenses/LICENSE
openff_nagl_models-2025.9.0.dist-info/METADATA
openff_nagl_models-2025.9.0.dist-info/WHEEL
openff_nagl_models-2025.9.0.dist-info/entry_points.txt
openff_nagl_models-2025.9.0.dist-info/top_level.txt
openff_nagl_models-2025.9.0.dist-info/RECORD
