Metadata-Version: 2.4
Name: openff-nagl-models
Version: 2025.9.0
Summary: OpenFF NAGL Models
Author-email: Lily Wang <lily.wang@openforcefield.org>
Maintainer-email: Lily Wang <lily.wang@openforcefield.org>
License: Copyright (c) 2023, Open Forcefield Group
Project-URL: Documentation, https://openff-nagl-models.readthedocs.io
Project-URL: Repository, https://github.com/openforcefield/openff-nagl-models
Classifier: Programming Language :: Python :: 3 :: Only
Classifier: Programming Language :: Python :: 3.11
Classifier: Programming Language :: Python :: 3.12
Classifier: Programming Language :: Python :: 3.13
Requires-Python: >=3.11
License-File: LICENSE
Requires-Dist: packaging
Requires-Dist: platformdirs
Provides-Extra: test
Requires-Dist: numpy; extra == "test"
Requires-Dist: pytest>=6; extra == "test"
Dynamic: license-file
